MANIFEST.in
README.rst
pipin.py
requirements.txt
setup.py
pipin_req.egg-info/PKG-INFO
pipin_req.egg-info/SOURCES.txt
pipin_req.egg-info/dependency_links.txt
pipin_req.egg-info/entry_points.txt
pipin_req.egg-info/requires.txt
pipin_req.egg-info/top_level.txt