Metadata-Version: 1.1
Name: pipin-req
Version: 0.1.4
Summary: Pin versions in requirements file
Home-page: https://github.com/Shir0kamii/pipin
Author: Shir0kamii
Author-email: shir0kamii@gmail.com
License: MIT
Keywords: pip requirements requirement pin versions version
Platform: UNKNOWN
Classifier: Environment :: Console
Classifier: Intended Audience :: Developers
Classifier: License :: OSI Approved :: MIT License
Classifier: Programming Language :: Python :: 2
Classifier: Programming Language :: Python :: 2.7
Classifier: Programming Language :: Python :: 3
Classifier: Programming Language :: Python :: 3.3
Classifier: Programming Language :: Python :: 3.4
Classifier: Programming Language :: Python :: 3.5
Classifier: Programming Language :: Python :: 3.6
Classifier: Programming Language :: Python :: 3.7
Classifier: Topic :: Software Development :: Documentation
